README.rst
setup.py
rrc_sentry_dingding_robot.egg-info/PKG-INFO
rrc_sentry_dingding_robot.egg-info/SOURCES.txt
rrc_sentry_dingding_robot.egg-info/dependency_links.txt
rrc_sentry_dingding_robot.egg-info/entry_points.txt
rrc_sentry_dingding_robot.egg-info/not-zip-safe
rrc_sentry_dingding_robot.egg-info/requires.txt
rrc_sentry_dingding_robot.egg-info/top_level.txt
sentry_dingding/__init__.py
sentry_dingding/models.py